zibal/__init__.py
zibal/client.py
zibal/configs.py
zibal/exceptions.py
zibal/models/__init__.py
zibal/models/schemas.py
zibal/response_codes.py
zibal/utils.py
zibal_client-0.3.3.dist-info/LICENSE
zibal_client-0.3.3.dist-info/METADATA
zibal_client-0.3.3.dist-info/WHEEL
zibal_client-0.3.3.dist-info/RECORD
