Metadata-Version: 2.1
Name: zibal-client
Version: 0.3.3
Summary: Client for interacting with Zibal's IPG API endpoints.
Home-page: https://github.com/Shebeli/zibal-client
License: MIT
Author: Shervin
Author-email: Shervinsaeedi78@gmail.com
Requires-Python: >=3.9,<4.0
Classifier: License :: OSI Approved :: MIT License
Classifier: Programming Language :: Python :: 3
Classifier: Programming Language :: Python :: 3.9
Classifier: Programming Language :: Python :: 3.10
Classifier: Programming Language :: Python :: 3.11
Classifier: Programming Language :: Python :: 3.12
Classifier: Programming Language :: Python :: 3.13
Requires-Dist: mypy (>=1.11.2,<2.0.0)
Requires-Dist: pydantic (>=2.8.2,<3.0.0)
Requires-Dist: requests (>=2.32.3,<3.0.0)
Requires-Dist: types-requests (>=2.32.0.20240712,<3.0.0.0)
Project-URL: Repository, https://github.com/Shebeli/zibal-client
